ligo_lvalert_overseer-0.1.3-nspkg.pth
ligo/overseer/__init__.py
ligo/overseer/lvalert_client.py
ligo/overseer/overseer_client.py
ligo_lvalert_overseer-0.1.3.data/scripts/lvalert_overseer
ligo_lvalert_overseer-0.1.3.data/scripts/overseer_test_client
ligo_lvalert_overseer-0.1.3.dist-info/DESCRIPTION.rst
ligo_lvalert_overseer-0.1.3.dist-info/METADATA
ligo_lvalert_overseer-0.1.3.dist-info/RECORD
ligo_lvalert_overseer-0.1.3.dist-info/WHEEL
ligo_lvalert_overseer-0.1.3.dist-info/metadata.json
ligo_lvalert_overseer-0.1.3.dist-info/namespace_packages.txt
ligo_lvalert_overseer-0.1.3.dist-info/top_level.txt
