Metadata-Version: 2.0
Name: ligo-lvalert-overseer
Version: 0.1.3
Summary: LVAlert Overseer Server and Client Tools
Home-page: UNKNOWN
Author: Branson Stephens
Author-email: branson.stephens@ligo.org
License: GPLv3
Platform: UNKNOWN
Requires-Dist: ligo-lvalert
Requires-Dist: pyxmpp
Requires-Dist: twisted
